Workbook
Name ARP: '[1]Datos Básicos'!$F$9
Name AT: '[1]Datos Básicos'!$B$6
Name CAJA: '[1]Datos Básicos'!$B$11
Name Cesantia: '[1]Datos Básicos'!$B$19
Name ESAP: '[1]Datos Básicos'!$F$15
Name FonSol1: '[1]Datos Básicos'!$B$26
Name FonSol2: '[1]Datos Básicos'!$B$27
Name FonSol3: '[1]Datos Básicos'!$B$28
Name FonSol4: '[1]Datos Básicos'!$B$29
Name FonSol5: '[1]Datos Básicos'!$B$30
Name FonSol6: '[1]Datos Básicos'!$B$31
Name ICBF: '[1]Datos Básicos'!$B$10
Name IND: '[1]Datos Básicos'!$F$16
Name IntCesantia: '[1]Datos Básicos'!$B$22
Name PensionEmpleado: '[1]Datos Básicos'!$B$16
Name PensionEmpresa: '[1]Datos Básicos'!$C$16
Name Prima: '[1]Datos Básicos'!$B$20
Name SaludEmpleado: '[1]Datos Básicos'!$B$15
Name SaludEmpresa: '[1]Datos Básicos'!$C$15
Name SENA: '[1]Datos Básicos'!$B$9
Name SM: '[1]Datos Básicos'!$B$5
Name UVT: '[1]Datos Básicos'!$F$11
Name Vacaciones: '[1]Datos Básicos'!$B$21
Name ValorHora: [1]Calculos!$B$4

Sheet PRODUC ACUMULADA
A2: PRODUCCION MES
A4: MES | B4: PRODUCCION
A5: ENERO | B5: =+'[2]PRODUC ACUMULADA'!$B$5 -> 1698.66
A6: FEBRERO | B6: 1830.15
A7: MARZO | B7: =+'[3]PRODUC ACUMULADA'!$B$7 -> 1898.77
A8: ABRIL | B8: 1800.91
A9: MAYO | B9: =+'[5]PRODUC ACUMULADA'!$B$9 -> 1964.11
A10: JUNIO | B10: =+'[5]PRODUC ACUMULADA'!$B$10 -> 926.97
A11: JULIO | B11: =+'[5]PRODUC ACUMULADA'!$B$11 -> 0
A12: AGOSTO | B12: =+'[5]PRODUC ACUMULADA'!$B$12 -> 0
A13: SEPTIEMBRE | B13: =+'[5]PRODUC ACUMULADA'!$B$13 -> 0
A14: OCTUBRE | B14: =+'[5]PRODUC ACUMULADA'!$B$14 -> 0
A15: NOVIEMBRE | B15: =+'[5]PRODUC ACUMULADA'!$B$15 -> 0
A16: DICIEMBRE | B16: =+'[5]PRODUC ACUMULADA'!$B$16 -> 0
A17: TOTAL | B17: =SUM(B5:B16) -> 10119.57

Sheet COSTOS EPP
A1: EPP | B1: PRECIO UNITARIO | C1: ENERO | D1: FEBRERO | E1: MARZO | F1: ABRIL | G1: MAYO | H1: JUNIO | I1: JULIO | J1: AGOSTO | K1: SEPTIEMBRE | L1: OCTUBRE | M1: NOVIEMBRE | N1: DICIEMBRE | O1: TOTAL UNID AÑO | P1: PRECIO UNITARIO | Q1: TOTAL V/R AÑO | R1: ENERO | S1: FEBRERO | T1: MARZO | U1: ABRIL | V1: MAYO | W1: JUNIO | X1: JULIO | Y1: AGOSTO | Z1: SEPTIEMBRE | AA1: OCTUBRE | AB1: NOVIEMBRE | AC1: DICIEMBRE
A2: GUANTES CARNAZA | B2: 9200 | C2: 6 | D2: 12 | E2: 24 | F2: 24 | G2: 12 | H2: 0 | I2: 0 | J2: 0 | K2: 0 | L2: 0 | M2: 0 | O2: =+C2+D2+E2+F2+G2+H2+I2+J2+K2+L2+M2+N2 -> 78 | P2: =+B2 -> 9200 | Q2: =+O2*P2 -> 717600 | R2: =+C2*P2 -> 55200 | S2: =B2*D2 -> 110400 | T2: =B2*E2 -> 220800 | U2: =B2*F2 -> 220800 | V2: =B2*G2 -> 110400 | W2: =B2*H2 -> 0 | X2: =B2*I2 -> 0 | Y2: =J2*B2 -> 0 | Z2: =B2*K2 -> 0 | AA2: =B2*L2 -> 0 | AB2: =M2*B2 -> 0 | AC2: =B2*N2 -> 0
A3: TAFILETE DE ROSCA | B3: 14000 | C3: 0 | D3: 0 | E3: 7 | F3: 23 | G3: 0 | H3: 0 | I3: 0 | J3: 0 | K3: 0 | L3: 0 | M3: 0 | N3: 0 | O3: =+C3+D3+E3+F3+G3+H3+I3+J3+K3+L3+M3+N3 -> 30 | P3: =+B3 -> 14000 | Q3: =+O3*P3 -> 420000 | R3: =+C3*P3 -> 0 | S3: =B3*D3 -> 0 | T3: =B3*E3 -> 98000 | U3: =B3*F3 -> 322000 | V3: =B3*G3 -> 0 | W3: =B3*H3 -> 0 | X3: =B3*I3 -> 0 | Y3: =J3*B3 -> 0 | Z3: =B3*K3 -> 0 | AA3: =B3*L3 -> 0 | AB3: =M3*B3 -> 0 | AC3: =B3*N3 -> 0
A4: FILTROS 7093C | B4: 63000 | C4: 12 | D4: 17 | E4: =27+16 -> 43 | F4: 34 | G4: 2 | H4: 0 | I4: 0 | J4: 0 | K4: 0 | L4: 0 | M4: 0 | N4: 0 | O4: =+C4+D4+E4+F4+G4+H4+I4+J4+K4+L4+M4+N4 -> 108 | P4: =+B4 -> 63000 | Q4: =+O4*P4 -> 6804000 | R4: =+C4*P4 -> 756000 | S4: =B4*D4 -> 1071000 | T4: =B4*E4 -> 2709000 | U4: =B4*F4 -> 2142000 | V4: =B4*G4 -> 126000 | W4: =B4*H4 -> 0 | X4: =B4*I4 -> 0 | Y4: =J4*B4 -> 0 | Z4: =B4*K4 -> 0 | AA4: =B4*L4 -> 0 | AB4: =M4*B4 -> 0 | AC4: =B4*N4 -> 0
A5: GUANTES NITRILO | B5: 5500 | C5: 0 | D5: 6 | E5: 0 | F5: 12 | G5: 0 | H5: 0 | I5: 0 | J5: 0 | K5: 0 | L5: 0 | M5: 0 | N5: 0 | O5: =+C5+D5+E5+F5+G5+H5+I5+J5+K5+L5+M5+N5 -> 18 | P5: =+B5 -> 5500 | Q5: =+O5*P5 -> 99000 | R5: =+C5*P5 -> 0 | S5: =B5*D5 -> 33000 | T5: =B5*E5 -> 0 | U5: =B5*F5 -> 66000 | V5: =B5*G5 -> 0 | W5: =B5*H5 -> 0 | X5: =B5*I5 -> 0 | Y5: =J5*B5 -> 0 | Z5: =B5*K5 -> 0 | AA5: =B5*L5 -> 0 | AB5: =M5*B5 -> 0 | AC5: =B5*N5 -> 0
A6: PROTECTOR AUDITIVO | B6: 39000 | C6: 0 | D6: 6 | E6: 12 | F6: 0 | G6: 0 | H6: 0 | I6: 0 | J6: 0 | K6: 0 | L6: 0 | M6: 0 | N6: 0 | O6: =+C6+D6+E6+F6+G6+H6+I6+J6+K6+L6+M6+N6 -> 18 | P6: =+B6 -> 39000 | Q6: =+O6*P6 -> 702000 | R6: =+C6*P6 -> 0 | S6: =B6*D6 -> 234000 | T6: =B6*E6 -> 468000 | U6: =B6*F6 -> 0 | V6: =B6*G6 -> 0 | W6: =B6*H6 -> 0 | X6: =B6*I6 -> 0 | Y6: =J6*B6 -> 0 | Z6: =B6*K6 -> 0 | AA6: =B6*L6 -> 0 | AB6: =M6*B6 -> 0 | AC6: =B6*N6 -> 0
A7: BOTAS CAÑA ALTA | B7: 61800 | C7: 11 | D7: 17 | E7: 24 | F7: 23 | G7: 13 | H7: 0 | I7: 0 | J7: 0 | K7: 0 | L7: 0 | M7: 0 | N7: 0 | O7: =+C7+D7+E7+F7+G7+H7+I7+J7+K7+L7+M7+N7 -> 88 | P7: =+B7 -> 61800 | Q7: =+O7*P7 -> 5438400 | R7: =+C7*P7 -> 679800 | S7: =B7*D7 -> 1050600 | T7: =B7*E7 -> 1483200 | U7: =B7*F7 -> 1421400 | V7: =B7*G7 -> 803400 | W7: =B7*H7 -> 0 | X7: =B7*I7 -> 0 | Y7: =J7*B7 -> 0 | Z7: =B7*K7 -> 0 | AA7: =B7*L7 -> 0 | AB7: =M7*B7 -> 0 | AC7: =B7*N7 -> 0
A8: TAPA ODIO DE INSERCION | B8: 3500 | C8: 0 | D8: 18 | E8: 8 | F8: 18 | G8: 16 | H8: 0 | I8: 0 | J8: 0 | K8: 0 | L8: 0 | M8: 0 | N8: 0 | O8: =+C8+D8+E8+F8+G8+H8+I8+J8+K8+L8+M8+N8 -> 60 | P8: =+B8 -> 3500 | Q8: =+O8*P8 -> 210000 | R8: =+C8*P8 -> 0 | S8: =B8*D8 -> 63000 | T8: =B8*E8 -> 28000 | U8: =B8*F8 -> 63000 | V8: =B8*G8 -> 56000 | W8: =B8*H8 -> 0 | X8: =B8*I8 -> 0 | Y8: =J8*B8 -> 0 | Z8: =B8*K8 -> 0 | AA8: =B8*L8 -> 0 | AB8: =M8*B8 -> 0 | AC8: =B8*N8 -> 0
A9: LAMPARAS KL6 | B9: 150000 | C9: 0 | D9: 2 | E9: 7 | F9: 4 | G9: 0 | H9: 0 | I9: 0 | J9: 0 | K9: 0 | L9: 0 | M9: 0 | N9: 0 | O9: =+C9+D9+E9+F9+G9+H9+I9+J9+K9+L9+M9+N9 -> 13 | P9: =+B9 -> 150000 | Q9: =+O9*P9 -> 1950000 | R9: =+C9*P9 -> 0 | S9: =B9*D9 -> 300000 | T9: =B9*E9 -> 1050000 | U9: =B9*F9 -> 600000 | V9: =B9*G9 -> 0 | W9: =B9*H9 -> 0 | X9: =B9*I9 -> 0 | Y9: =J9*B9 -> 0 | Z9: =B9*K9 -> 0 | AA9: =B9*L9 -> 0 | AB9: =M9*B9 -> 0 | AC9: =B9*N9 -> 0
A10: CASCOS | B10: 26000 | C10: 0 | D10: 0 | E10: 0 | F10: 1 | G10: 0 | H10: 0 | I10: 0 | J10: 0 | K10: 0 | L10: 0 | M10: 0 | N10: 0 | O10: =+C10+D10+E10+F10+G10+H10+I10+J10+K10+L10+M10+N10 -> 1 | P10: =+B10 -> 26000 | Q10: =+O10*P10 -> 26000 | R10: =+C10*P10 -> 0 | S10: =B10*D10 -> 0 | T10: =B10*E10 -> 0 | U10: =B10*F10 -> 26000 | V10: =B10*G10 -> 0 | W10: =B10*H10 -> 0 | X10: =B10*I10 -> 0 | Y10: =J10*B10 -> 0 | Z10: =B10*K10 -> 0 | AA10: =B10*L10 -> 0 | AB10: =M10*B10 -> 0 | AC10: =B10*N10 -> 0
A11: MASCARILLA 3M | B11: 77000 | C11: 2 | D11: 6 | E11: 22 | F11: 10 | G11: 0 | H11: 0 | I11: 0 | J11: 0 | K11: 0 | L11: 0 | M11: 0 | N11: 0 | O11: =+C11+D11+E11+F11+G11+H11+I11+J11+K11+L11+M11+N11 -> 40 | P11: =+B11 -> 77000 | Q11: =+O11*P11 -> 3080000 | R11: =+C11*P11 -> 154000 | S11: =B11*D11 -> 462000 | T11: =B11*E11 -> 1694000 | U11: =B11*F11 -> 770000 | V11: =B11*G11 -> 0 | W11: =B11*H11 -> 0 | X11: =B11*I11 -> 0 | Y11: =J11*B11 -> 0 | Z11: =B11*K11 -> 0 | AA11: =B11*L11 -> 0 | AB11: =M11*B11 -> 0 | AC11: =B11*N11 -> 0
A12: BOTAS DE MATERIAL | B12: 72000 | C12: 0 | D12: 0 | E12: 0 | F12: 0 | G12: 0 | H12: 0 | I12: 0 | J12: 0 | K12: 0 | L12: 0 | M12: 0 | N12: 0 | O12: =+C12+D12+E12+F12+G12+H12+I12+J12+K12+L12+M12+N12 -> 0 | P12: =+B12 -> 72000 | Q12: =+O12*P12 -> 0 | R12: =+C12*P12 -> 0 | S12: =B12*D12 -> 0 | T12: =B12*E12 -> 0 | U12: =B12*F12 -> 0 | V12: =B12*G12 -> 0 | W12: =B12*H12 -> 0 | X12: =B12*I12 -> 0 | Y12: =J12*B12 -> 0 | Z12: =B12*K12 -> 0 | AA12: =B12*L12 -> 0 | AB12: =M12*B12 -> 0 | AC12: =B12*N12 -> 0
A13: GAFAS NEGRAS | B13: 12000 | C13: 0 | D13: 0 | E13: 0 | F13: 0 | G13: 0 | H13: 0 | I13: 0 | J13: 0 | K13: 0 | L13: 0 | M13: 0 | N13: 0 | O13: =+C13+D13+E13+F13+G13+H13+I13+J13+K13+L13+M13+N13 -> 0 | P13: =+B13 -> 12000 | Q13: =+O13*P13 -> 0 | R13: =+C13*P13 -> 0 | S13: =B13*D13 -> 0 | T13: =B13*E13 -> 0 | U13: =B13*F13 -> 0 | V13: =B13*G13 -> 0 | W13: =B13*H13 -> 0 | X13: =B13*I13 -> 0 | Y13: =J13*B13 -> 0 | Z13: =B13*K13 -> 0 | AA13: =B13*L13 -> 0 | AB13: =M13*B13 -> 0 | AC13: =B13*N13 -> 0
A14: BARBUQUEJOS 4 PUNTOS | B14: 11000 | C14: 0 | D14: 0 | E14: 0 | F14: 0 | G14: 0 | H14: 0 | I14: 0 | J14: 0 | K14: 0 | L14: 0 | M14: 0 | N14: 0 | O14: =+C14+D14+E14+F14+G14+H14+I14+J14+K14+L14+M14+N14 -> 0 | P14: =+B14 -> 11000 | Q14: =+O14*P14 -> 0 | R14: =+C14*P14 -> 0 | S14: =B14*D14 -> 0 | T14: =B14*E14 -> 0 | U14: =B14*F14 -> 0 | V14: =B14*G14 -> 0 | W14: =B14*H14 -> 0 | X14: =B14*I14 -> 0 | Y14: =J14*B14 -> 0 | Z14: =B14*K14 -> 0 | AA14: =B14*L14 -> 0 | AB14: =M14*B14 -> 0 | AC14: =B14*N14 -> 0
A15: GUANTES DE IMPACTO | B15: 90000 | C15: 0 | D15: 0 | E15: 0 | F15: 18 | G15: 0 | H15: 0 | I15: 0 | J15: 0 | K15: 0 | L15: 0 | M15: 0 | N15: 0 | O15: =+C15+D15+E15+F15+G15+H15+I15+J15+K15+L15+M15+N15 -> 18 | P15: =+B15 -> 90000 | Q15: =+O15*P15 -> 1620000 | R15: =+C15*P15 -> 0 | S15: =B15*D15 -> 0 | T15: =B15*E15 -> 0 | U15: =B15*F15 -> 1620000 | V15: =B15*G15 -> 0 | W15: =B15*H15 -> 0 | X15: =B15*I15 -> 0 | Y15: =J15*B15 -> 0 | Z15: =B15*K15 -> 0 | AA15: =B15*L15 -> 0 | AB15: =M15*B15 -> 0 | AC15: =B15*N15 -> 0
A16: FILTROS 2091 ROSADOS | B16: 75000 | C16: 0 | D16: 0 | E16: 0 | F16: 0 | G16: 0 | H16: 0 | I16: 0 | J16: 0 | K16: 0 | L16: 0 | M16: 0 | N16: 0 | O16: =+C16+D16+E16+F16+G16+H16+I16+J16+K16+L16+M16+N16 -> 0 | P16: =+B16 -> 75000 | Q16: =+O16*P16 -> 0 | R16: =+C16*P16 -> 0 | S16: =B16*D16 -> 0 | T16: =B16*E16 -> 0 | U16: =B16*F16 -> 0 | V16: =B16*G16 -> 0 | W16: =B16*H16 -> 0 | X16: =B16*I16 -> 0 | Y16: =J16*B16 -> 0 | Z16: =B16*K16 -> 0 | AA16: =B16*L16 -> 0 | AB16: =M16*B16 -> 0 | AC16: =B16*N16 -> 0
... A20: GAFAS PROTECTORAS 3M | B20: 42000 | C20: 0 | D20: 0 | E20: 0 | F20: 0 | G20: 0 | H20: 0 | I20: 0 | J20: 0 | K20: 0 | L20: 0 | M20: 0 | N20: 0 | O20: =+C20+D20+E20+F20+G20+H20+I20+J20+K20+L20+M20+N20 -> 0 | P20: =+B20 -> 42000 | Q20: =+O20*P20 -> 0 | R20: =+C20*P20 -> 0 | S20: =B20*D20 -> 0 | T20: =B20*E20 -> 0 | U20: =B20*F20 -> 0 | V20: =B20*G20 -> 0 | W20: =B20*H20 -> 0 | X20: =B20*I20 -> 0 | Y20: =J20*B20 -> 0 | Z20: =B20*K20 -> 0 | AA20: =B20*L20 -> 0 | AB20: =M20*B20 -> 0 | AC20: =B20*N20 -> 0
A21: HOMBRERAS | B21: 124000 | C21: 0 | D21: 2 | E21: 0 | F21: 0 | G21: 0 | H21: 0 | I21: 0 | J21: 0 | K21: 0 | L21: 0 | M21: 0 | N21: 0 | O21: =+C21+D21+E21+F21+G21+H21+I21+J21+K21+L21+M21+N21 -> 2 | P21: =+B21 -> 124000 | Q21: =+O21*P21 -> 248000 | R21: =+C21*P21 -> 0 | S21: =B21*D21 -> 248000 | T21: =B21*E21 -> 0 | U21: =B21*F21 -> 0 | V21: =B21*G21 -> 0 | W21: =B21*H21 -> 0 | X21: =B21*I21 -> 0 | Y21: =J21*B21 -> 0 | Z21: =B21*K21 -> 0 | AA21: =B21*L21 -> 0 | AB21: =M21*B21 -> 0
A22: GAFAS DE MALLA | B22: 55000 | C22: 0 | D22: 0 | E22: 0 | F22: 0 | G22: 0 | H22: 0 | I22: 0 | J22: 0 | K22: 0 | L22: 0 | M22: 0 | N22: 0 | O22: =+C22+D22+E22+F22+G22+H22+I22+J22+K22+L22+M22+N22 -> 0 | P22: =+B22 -> 55000 | Q22: =+O22*P22 -> 0 | R22: =+C22*P22 -> 0 | S22: =B22*D22 -> 0 | T22: =B22*E22 -> 0 | U22: =B22*F22 -> 0 | V22: =B22*G22 -> 0 | W22: =B22*H22 -> 0 | X22: =B22*I22 -> 0 | Y22: =J22*B22 -> 0 | Z22: =B22*K22 -> 0 | AA22: =B22*L22 -> 0 | AB22: =M22*B22 -> 0 | AC22: =B22*N22 -> 0
B23: TOTAL | O23: =SUM(O2:O22) -> 510 | Q23: =SUM(Q2:Q22) -> 22053000 | R23: =SUM(R2:R22) -> 1645000 | S23: =SUM(S2:S22) -> 3818000 | T23: =SUM(T2:T22) -> 7751000 | U23: =SUM(U2:U22) -> 7743200 | V23: =SUM(V2:V22) -> 1095800 | W23: =SUM(W2:W22) -> 0 | X23: =SUM(X2:X22) -> 0 | ... AC23: =SUM(AC2:AC22) -> 0
B26: V/R INSUMOS | C26: TON | D26: V/R * TONELADA
A27: =+C1 -> ENERO | B27: =+R23 -> 1645000 | C27: =+'PRODUC ACUMULADA'!B5 -> 1698.66 | D27: =+B27/C27 -> 968.41039
A28: =+D1 -> FEBRERO | B28: =+S23 -> 3818000 | C28: =+'PRODUC ACUMULADA'!B6 -> 1830.15 | D28: =+B28/C28 -> 2086.1678
A29: =+E1 -> MARZO | B29: =+T23 -> 7751000 | C29: =+'PRODUC ACUMULADA'!B7 -> 1898.77 | D29: =+B29/C29 -> 4082.1163
A30: =+F1 -> ABRIL | B30: =+U23 -> 7743200 | C30: =+'PRODUC ACUMULADA'!B8 -> 1800.91 | D30: =+B30/C30 -> 4299.6041
A31: =+G1 -> MAYO | B31: =+V23 -> 1095800 | C31: =+'PRODUC ACUMULADA'!B9 -> 1964.11 | D31: =+B31/C31 -> 557.91173
A32: =+H1 -> JUNIO | B32: =+W23 -> 0 | C32: =+'PRODUC ACUMULADA'!B10 -> 926.97 | D32: =+B32/C32 -> 0
A33: =+I1 -> JULIO | B33: =+X23 -> 0 | C33: =+'PRODUC ACUMULADA'!B11 -> 0 | D33: =+B33/C33 -> #DIV/0!
A34: =+J1 -> AGOSTO | B34: =+Y23 -> 0 | C34: =+'PRODUC ACUMULADA'!B12 -> 0 | D34: =+B34/C34 -> #DIV/0!
A35: =+K1 -> SEPTIEMBRE | B35: =+Z23 -> 0 | C35: =+'PRODUC ACUMULADA'!B13 -> 0 | D35: =+B35/C35 -> #DIV/0!
A36: =+L1 -> OCTUBRE | B36: =+AA23 -> 0 | C36: =+'PRODUC ACUMULADA'!B14 -> 0 | D36: =+B36/C36 -> #DIV/0!
A37: =+M1 -> NOVIEMBRE | B37: =+AB23 -> 0 | C37: =+'PRODUC ACUMULADA'!B15 -> 0 | D37: =+B37/C37 -> #DIV/0!
A38: =+N1 -> DICIEMBRE | B38: =+AC23 -> 0 | C38: =+'PRODUC ACUMULADA'!B16 -> 0 | D38: =+B38/C38 -> #DIV/0!
A39: TOTALES | B39: =SUM(B27:B38) -> 22053000 | C39: =SUM(C27:C38) -> 10119.57 | D39: =SUM(D27:D38) -> #DIV/0!

Sheet COSTOS INSUMOS 
B1: INSUMOS | C1: ENERO | D1: FEBRERO | E1: MARZO | F1: ABRIL | G1: MAYO | H1: JUNIO | I1: JULIO | J1: AGOSTO | K1: SEPTIEMBRE | L1: OCTUBRE | M1: NOVIEMBRE | N1: DICIEMBRE | O1: TOTAL | P1: PRECIO UNITARIO | Q1: TOTAL | R1: ENERO EN PESOS | S1: FEBRERO EN PESOS | T1: MARZO EN PESOS | U1: ABRIL EN PESOS | V1: MAYO EN PESOS | W1: JUNIO EN PESOS | X1: JULIO EN PESOS | Y1: AGOSTO EN PESOS | Z1: SEPTIEMBRE EN PESOS | AA1: OCTUBRE EN PESOS | AB1: NOVIEMBRE EN PESOS | AC1: DICIEMBRE EN PESOS
B2: ITEM | C2: ENERO | D2: FEBRERO | E2: MARZO | F2: ABRIL | G2: MAYO | H2: JUNIO | I2: JULIO | J2: AGOSTO | K2: SEPTIEMBRE | L2: OCTUBRE | M2: NOVIEMBRE | N2: DICIEMBRE | O2: TOTAL | P2: PRECIO UNITARIO | Q2: TOTAL | R2: ENERO EN PESOS | S2: FEBRERO EN PESOS | T2: MARZO EN PESOS | U2: ABRIL EN PESOS | V2: MAYO EN PESOS | W2: JUNIO EN PESOS | X2: JULIO EN PESOS | Y2: AGOSTO EN PESOS | Z2: SEPTIEMBRE EN PESOS | AA2: OCTUBRE EN PESOS | AB2: NOVIEMBRE EN PESOS | AC2: DICIEMBRE EN PESOS
B3: abrazadera industrial (500 y 501) | C3: 34 | E3: 64 | F3: 50 | G3: 20 | O3: =SUM(C3:N3) -> 168 | P3: 3720 | Q3: =O3*P3 -> 624960 | R3: =C3*P3 -> 126480 | S3: =+D3*P3 -> 0 | T3: =+E3*P3 -> 238080 | U3: =+F3*P3 -> 186000 | V3: =+G3*P3 -> 74400
B4: acople espigo macho 3/4 | C4: 6 | D4: 3 | E4: 6 | F4: 6 | G4: 9 | O4: =SUM(C4:N4) -> 30 | P4: 9789 | Q4: =O4*P4 -> 293670 | R4: =C4*P4 -> 58734 | S4: =+D4*P4 -> 29367 | T4: =+E4*P4 -> 58734 | U4: =+F4*P4 -> 58734 | V4: =+G4*P4 -> 88101
B5: cinta ducto | C5: 7 | E5: 9 | G5: 6 | O5: =SUM(C5:N5) -> 22 | P5: 17621 | Q5: =O5*P5 -> 387662 | R5: =C5*P5 -> 123347 | S5: =+D5*P5 -> 0 | T5: =+E5*P5 -> 158589 | U5: =+F5*P5 -> 0 | V5: =+G5*P5 -> 105726
B6: clavos de riel | C6: 500 | E6: 750 | F6: 750 | G6: 500 | O6: =SUM(C6:N6) -> 2500 | P6: 783 | Q6: =O6*P6 -> 1957500 | R6: =C6*P6 -> 391500 | S6: =+D6*P6 -> 0 | T6: =+E6*P6 -> 587250 | U6: =+F6*P6 -> 587250 | V6: =+G6*P6 -> 391500
B7: puntilla vareta | C7: 6 | E7: 2 | F7: 9 | O7: =SUM(C7:N7) -> 17 | P7: 13000 | Q7: =O7*P7 -> 221000 | R7: =C7*P7 -> 78000 | S7: =+D7*P7 -> 0 | T7: =+E7*P7 -> 26000 | U7: =+F7*P7 -> 117000 | V7: =+G7*P7 -> 0
B8: hoja de cegueta | C8: 11 | E8: 5 | O8: =SUM(C8:N8) -> 16 | P8: 5100 | Q8: =O8*P8 -> 81600 | R8: =C8*P8 -> 56100 | S8: =+D8*P8 -> 0 | T8: =+E8*P8 -> 25500 | U8: =+F8*P8 -> 0 | V8: =+G8*P8 -> 0
B9: lima triangular | C9: 11 | E9: 7 | F9: 10 | G9: 10 | O9: =SUM(C9:N9) -> 38 | P9: 6000 | Q9: =O9*P9 -> 228000 | R9: =C9*P9 -> 66000 | S9: =+D9*P9 -> 0 | T9: =+E9*P9 -> 42000 | U9: =+F9*P9 -> 60000 | V9: =+G9*P9 -> 60000
B10: porro | C10: 1 | E10: 2 | F10: 3 | G10: 1 | O10: =SUM(C10:N10) -> 7 | P10: 101815 | Q10: =C10*P10 -> 101815 | R10: =C10*P10 -> 101815 | S10: =+D10*P10 -> 0 | T10: =+E10*P10 -> 203630 | U10: =+F10*P10 -> 305445 | V10: =+G10*P10 -> 101815
B11: varilla de admision m 37 | C11: 8 | F11: 6 | O11: =SUM(C11:N11) -> 14 | P11: 3915 | Q11: =O11*P11 -> 54810 | R11: =C11*P11 -> 31320 | S11: =+D11*P11 -> 0 | T11: =+E11*P11 -> 0 | U11: =+F11*P11 -> 23490 | V11: =+G11*P11 -> 0
B12: pala minera | C12: 2 | E12: 4 | G12: 2 | O12: =SUM(C12:N12) -> 8 | P12: 68500 | Q12: =O12*P12 -> 548000 | R12: =C12*P12 -> 137000 | S12: =+D12*P12 -> 0 | T12: =+E12*P12 -> 274000 | U12: =+F12*P12 -> 0 | V12: =+G12*P12 -> 137000
B13: perno 3/4 | C13: 6 | E13: 8 | F13: 10 | O13: =SUM(C13:N13) -> 24 | P13: 11789 | Q13: =O13*P13 -> 282936 | R13: =C13*P13 -> 70734 | S13: =+D13*P13 -> 0 | T13: =+E13*P13 -> 94312 | U13: =+F13*P13 -> 117890 | V13: =+G13*P13 -> 0
B14: puntilla 3" | C14: 7 | E14: 3 | G14: 3 | O14: =SUM(C14:N14) -> 13 | P14: 5100 | Q14: =O14*P14 -> 66300 | R14: =C14*P14 -> 35700 | S14: =+D14*P14 -> 0 | T14: =+E14*P14 -> 15300 | U14: =+F14*P14 -> 0 | V14: =+G14*P14 -> 15300
B15: puntilla 5" | C15: 2 | O15: =SUM(C15:N15) -> 2 | P15: 10768 | Q15: =O15*P15 -> 21536 | R15: =C15*P15 -> 21536 | S15: =+D15*P15 -> 0 | T15: =+E15*P15 -> 0 | U15: =+F15*P15 -> 0 | V15: =+G15*P15 -> 0
B16: puntilla 6" | C16: 5 | F16: 5 | O16: =SUM(C16:N16) -> 10 | P16: 10768 | Q16: =O16*P16 -> 107680 | R16: =C16*P16 -> 53840 | S16: =+D16*P16 -> 0 | T16: =+E16*P16 -> 0 | U16: =+F16*P16 -> 53840 | V16: =+G16*P16 -> 0
B17: RESORTE DE SUJECCION PARA MARTILLO 8.5KG | C17: 6 | O17: =SUM(C17:N17) -> 6 | P17: 8000 | Q17: =O17*P17 -> 48000 | R17: =C17*P17 -> 48000 | S17: =+D17*P17 -> 0 | T17: =+E17*P17 -> 0 | U17: =+F17*P17 -> 0 | V17: =+G17*P17 -> 0
B18: AEROSOL | C18: 4 | E18: 4 | F18: 9 | O18: =SUM(C18:N18) -> 17 | P18: 11750 | Q18: =O18*P18 -> 199750 | R18: =C18*P18 -> 47000 | S18: =+D18*P18 -> 0 | T18: =+E18*P18 -> 47000 | U18: =+F18*P18 -> 105750 | V18: =+G18*P18 -> 0
B19: TEE RAPIDA 3/4 interplast | C19: 2 | O19: =SUM(C19:N19) -> 2 | P19: 17621 | Q19: =O19*P19 -> 35242 | R19: =C19*P19 -> 35242 | S19: =+D19*P19 -> 0 | T19: =+E19*P19 -> 0 | U19: =+F19*P19 -> 0 | V19: =+G19*P19 -> 0
B20: unon rapida 3/4 | C20: 4 | E20: 8 | F20: 16 | G20: 6 | O20: =SUM(C20:N20) -> 34 | P20: 10573 | Q20: =O20*P20 -> 359482 | R20: =C20*P20 -> 42292 | S20: =+D20*P20 -> 0 | T20: =+E20*P20 -> 84584 | U20: =+F20*P20 -> 169168 | V20: =+G20*P20 -> 63438
B21: DIFERENCIAL DE CADENA CON PALANCA 3T | C21: 1 | O21: =SUM(C21:N21) -> 1 | P21: 567816 | Q21: =O21*P21 -> 567816 | R21: =C21*P21 -> 567816 | S21: =+D21*P21 -> 0 | T21: =+E21*P21 -> 0 | U21: =+F21*P21 -> 0 | V21: =+G21*P21 -> 0
B22: cinta aislante | C22: 10 | E22: 6 | G22: 1 | O22: =SUM(C22:N22) -> 17 | P22: 9000 | Q22: =O22*P22 -> 153000 | R22: =C22*P22 -> 90000 | S22: =+D22*P22 -> 0 | T22: =+E22*P22 -> 54000 | U22: =+F22*P22 -> 0 | V22: =+G22*P22 -> 9000
B23: ducto 18" | C23: 1 | F23: 1 | O23: =SUM(C23:N23) -> 2 | P23: 432714 | Q23: =O23*P23 -> 865428 | R23: =C23*P23 -> 432714 | S23: =+D23*P23 -> 0 | T23: =+E23*P23 -> 0 | U23: =+F23*P23 -> 432714 | V23: =+G23*P23 -> 0
B24: eclipsas con tornillo | C24: 36 | E24: 60 | F24: 60 | G24: 70 | O24: =SUM(C24:N24) -> 226 | P24: 19579 | Q24: =O24*P24 -> 4424854 | R24: =C24*P24 -> 704844 | S24: =+D24*P24 -> 0 | T24: =+E24*P24 -> 1174740 | U24: =+F24*P24 -> 1174740 | V24: =+G24*P24 -> 1370530
B25: manila de 1" mts | C25: 1 | E25: 1 | G25: 2 | H25: 0.5 | O25: =SUM(C25:N25) -> 4.5 | P25: 763613 | Q25: =O25*P25 -> 3436258.5 | R25: =C25*P25 -> 763613 | S25: =+D25*P25 -> 0 | T25: =+E25*P25 -> 763613 | U25: =+F25*P25 -> 0 | V25: =+G25*P25 -> 1527226
B26: punta para martillo m37 | C26: 8 | E26: 24 | G26: 8 | O26: =SUM(C26:N26) -> 40 | P26: 53844 | Q26: =O26*P26 -> 2153760 | R26: =C26*P26 -> 430752 | S26: =+D26*P26 -> 0 | T26: =+E26*P26 -> 1292256 | U26: =+F26*P26 -> 0 | V26: =+G26*P26 -> 430752
B27: Taco 40 w+ | C27: 1 | O27: =SUM(C27:N27) -> 1 | P27: 22600 | Q27: =O27*P27 -> 22600 | R27: =C27*P27 -> 22600 | S27: =+D27*P27 -> 0 | T27: =+E27*P27 -> 0 | U27: =+F27*P27 -> 0 | V27: =+G27*P27 -> 0
B28: BROCA HSS ANSI 9411 X 5/16 IW1124 IRWIN | C28: 3 | O28: =SUM(C28:N28) -> 3 | P28: 12750 | Q28: =O28*P28 -> 38250 | R28: =C28*P28 -> 38250 | S28: =+D28*P28 -> 0 | T28: =+E28*P28 -> 0 | U28: =+F28*P28 -> 0 | V28: =+G28*P28 -> 0
B29: BROCA HSS ANSI 9411 X 1/4 IW1120 IRWIN | C29: 4 | O29: =SUM(C29:N29) -> 4 | P29: 7900 | Q29: =O29*P29 -> 31600 | R29: =C29*P29 -> 31600 | S29: =+D29*P29 -> 0 | T29: =+E29*P29 -> 0 | U29: =+F29*P29 -> 0 | V29: =+G29*P29 -> 0
B30: BROCA HSS ANSI 9411 X 1/8 IW1112 IRWIN | C30: 3 | O30: =SUM(C30:N30) -> 3 | P30: 3500 | Q30: =O30*P30 -> 10500 | R30: =C30*P30 -> 10500 | S30: =+D30*P30 -> 0 | T30: =+E30*P30 -> 0 | U30: =+F30*P30 -> 0 | V30: =+G30*P30 -> 0
B31: BROCA HSS ANSI 9411 X 3/16 IW1116 IRWIN | C31: 3 | O31: =SUM(C31:N31) -> 3 | P31: 4900 | Q31: =O31*P31 -> 14700 | R31: =C31*P31 -> 14700 | S31: =+D31*P31 -> 0 | T31: =+E31*P31 -> 0 | U31: =+F31*P31 -> 0 | V31: =+G31*P31 -> 0
B32: BROCA HSS ANSI 9411 X 5/32 IW1114 IRWIN | C32: 3 | O32: =SUM(C32:N32) -> 3 | P32: 3933 | Q32: =O32*P32 -> 11799 | R32: =C32*P32 -> 11799 | S32: =+D32*P32 -> 0 | T32: =+E32*P32 -> 0 | U32: =+F32*P32 -> 0 | V32: =+G32*P32 -> 0
B33: rodamiento 6207 | C33: 20 | E33: 24 | F33: 25 | G33: 22 | O33: =SUM(C33:N33) -> 91 | P33: 10770 | Q33: =O33*P33 -> 980070 | R33: =C33*P33 -> 215400 | S33: =+D33*P33 -> 0 | T33: =+E33*P33 -> 258480 | U33: =+F33*P33 -> 269250 | V33: =+G33*P33 -> 236940
B34: rodamiento 6307 | C34: 32 | E34: 24 | F34: 24 | G34: 18 | O34: =SUM(C34:N34) -> 98 | P34: 16700 | Q34: =O34*P34 -> 1636600 | R34: =C34*P34 -> 534400 | S34: =+D34*P34 -> 0 | T34: =+E34*P34 -> 400800 | U34: =+F34*P34 -> 400800 | V34: =+G34*P34 -> 300600
B35: rodamiento 6208 | C35: 32 | G35: 10 | O35: =SUM(C35:N35) -> 42 | P35: 11800 | Q35: =O35*P35 -> 495600 | R35: =C35*P35 -> 377600 | S35: =+D35*P35 -> 0 | T35: =+E35*P35 -> 0 | U35: =+F35*P35 -> 0 | V35: =+G35*P35 -> 118000
B36: cilindro la cruz m37 | C36: 1 | G36: 1 | O36: =SUM(C36:N36) -> 2 | P36: 881092 | Q36: =O36*P36 -> 1762184 | R36: =C36*P36 -> 881092 | S36: =+D36*P36 -> 0 | T36: =+E36*P36 -> 0 | U36: =+F36*P36 -> 0 | V36: =+G36*P36 -> 881092
B37: union rapida 2" | C37: 5 | E37: 4 | O37: =SUM(C37:N37) -> 9 | P37: 54000 | Q37: =O37*P37 -> 486000 | R37: =C37*P37 -> 270000 | S37: =+D37*P37 -> 0 | T37: =+E37*P37 -> 216000 | U37: =+F37*P37 -> 0 | V37: =+G37*P37 -> 0
B38: manguera 3/4 petalizada | C38: 1 | E38: 1 | F38: 1 | G38: 2 | O38: =SUM(C38:N38) -> 5 | P38: 137100 | Q38: =O38*P38 -> 685500 | R38: =C38*P38 -> 137100 | S38: =+D38*P38 -> 0 | T38: =+E38*P38 -> 137100 | U38: =+F38*P38 -> 137100 | V38: =+G38*P38 -> 274200
B39: manigueta m37 | C39: 1 | E39: 1 | F39: 2 | O39: =SUM(C39:N39) -> 4 | P39: 1076890 | Q39: =O39*P39 -> 4307560 | R39: =C39*P39 -> 1076890 | S39: =+D39*P39 -> 0 | T39: =+E39*P39 -> 1076890 | U39: =+F39*P39 -> 2153780 | V39: =+G39*P39 -> 0
B40: riel 18 libras | C40: 41 | D40: 45 | F40: 21 | G40: 21 | O40: =SUM(C40:N40) -> 128 | P40: 275000 | Q40: =O40*P40 -> 35200000 | R40: =C40*P40 -> 11275000 | S40: =+D40*P40 -> 12375000 | T40: =+E40*P40 -> 0 | U40: =+F40*P40 -> 5775000 | V40: =+G40*P40 -> 5775000
B41: ducto 14" | C41: 1 | D41: 1 | F41: 1 | G41: 1 | O41: =SUM(C41:N41) -> 4 | P41: 426700 | Q41: =O41*P41 -> 1706800 | R41: =C41*P41 -> 426700 | S41: =+D41*P41 -> 426700 | T41: =+E41*P41 -> 0 | U41: =+F41*P41 -> 426700 | V41: =+G41*P41 -> 426700
B42: Silicona gris | C42: 3 | O42: =SUM(C42:N42) -> 3 | P42: 12726 | Q42: =O42*P42 -> 38178 | R42: =C42*P42 -> 38178 | S42: =+D42*P42 -> 0 | T42: =+E42*P42 -> 0 | U42: =+F42*P42 -> 0 | V42: =+G42*P42 -> 0
B43: estopa | C43: 2 | D43: 12 | O43: =SUM(C43:N43) -> 14 | P43: 7831 | Q43: =O43*P43 -> 109634 | R43: =C43*P43 -> 15662 | S43: =+D43*P43 -> 93972 | T43: =+E43*P43 -> 0 | U43: =+F43*P43 -> 0 | V43: =+G43*P43 -> 0
B44: puntilla 2" | C44: 3 | E44: 4 | F44: 2 | G44: 3 | O44: =SUM(C44:N44) -> 12 | P44: 15663 | Q44: =O44*P44 -> 187956 | R44: =C44*P44 -> 46989 | S44: =+D44*P44 -> 0 | T44: =+E44*P44 -> 62652 | U44: =+F44*P44 -> 31326 | V44: =+G44*P44 -> 46989
B45: empate | E45: 5 | O45: =SUM(C45:N45) -> 5 | P45: 9500 | Q45: =O45*P45 -> 47500 | S45: =+D45*P45 -> 0 | T45: =+E45*P45 -> 47500 | U45: =+F45*P45 -> 0 | V45: =+G45*P45 -> 0
B46: guio | C46: 1 | O46: =SUM(C46:N46) -> 1 | P46: 352436 | Q46: =O46*P46 -> 352436 | R46: =C46*P46 -> 352436 | S46: =+D46*P46 -> 0 | T46: =+E46*P46 -> 0 | U46: =+F46*P46 -> 0 | V46: =+G46*P46 -> 0
B47: abrazadera industrial 509 paq | C47: 1 | E47: 1 | O47: =SUM(C47:N47) -> 2 | P47: 37201 | Q47: =O47*P47 -> 74402 | R47: =C47*P47 -> 37201 | S47: =+D47*P47 -> 0 | T47: =+E47*P47 -> 37201 | U47: =+F47*P47 -> 0 | V47: =+G47*P47 -> 0
B48: AISLADORES DE PORCELANA | D48: 60 | O48: =SUM(D48:N48) -> 60 | P48: 6729 | Q48: =O48*P48 -> 403740 | R48: =C48*P48 -> 0 | S48: =+D48*P48 -> 403740 | T48: =+E48*P48 -> 0 | U48: =+F48*P48 -> 0 | V48: =+G48*P48 -> 0
B49: ARANDELAS 1 1/2 SEGURIDAD | D49: 12 | O49: =SUM(D49:N49) -> 12 | P49: 23205 | Q49: =O49*P49 -> 278460 | R49: =C49*P49 -> 0 | S49: =+D49*P49 -> 278460 | T49: =+E49*P49 -> 0 | U49: =+F49*P49 -> 0 | V49: =+G49*P49 -> 0
B50: ARANDELAS 3/16 | D50: 10 | O50: =SUM(D50:N50) -> 10 | P50: 186 | Q50: =O50*P50 -> 1860 | R50: =C50*P50 -> 0 | S50: =+D50*P50 -> 1860 | T50: =+E50*P50 -> 0 | U50: =+F50*P50 -> 0 | V50: =+G50*P50 -> 0
B51: CABLE SOLDADOR PARA MASA | D51: 8 | O51: =SUM(D51:N51) -> 8 | P51: 80444 | Q51: =O51*P51 -> 643552 | R51: =C51*P51 -> 0 | S51: =+D51*P51 -> 643552 | T51: =+E51*P51 -> 0 | U51: =+F51*P51 -> 0 | V51: =+G51*P51 -> 0
B52: CABLE 2 X 14 ESPECIAL | D52: 1 | F52: 1 | O52: =SUM(D52:N52) -> 2 | P52: 185640 | Q52: =O52*P52 -> 371280 | R52: =C52*P52 -> 0 | S52: =+D52*P52 -> 185640 | T52: =+E52*P52 -> 0 | U52: =+F52*P52 -> 185640 | V52: =+G52*P52 -> 0
B53: CINTA DE PELIGRO 500MTS | D53: 1 | O53: =SUM(D53:N53) -> 1 | P53: 39603 | Q53: =O53*P53 -> 39603 | R53: =C53*P53 -> 0 | S53: =+D53*P53 -> 39603 | T53: =+E53*P53 -> 0 | U53: =+F53*P53 -> 0 | V53: =+G53*P53 -> 0
B54: CINTA REFLECTIVO ROJO- BLANCO | D54: 1 | O54: =SUM(D54:N54) -> 1 | P54: 39603 | Q54: =O54*P54 -> 39603 | R54: =C54*P54 -> 0 | S54: =+D54*P54 -> 39603 | T54: =+E54*P54 -> 0 | U54: =+F54*P54 -> 0 | V54: =+G54*P54 -> 0
B55: SOLDADURA 7018 1/8 | D55: 5 | F55: 5 | G55: 5 | H55: 5 | O55: =SUM(D55:N55) -> 20 | P55: 102102 | Q55: =O55*P55 -> 2042040 | R55: =C55*P55 -> 0 | S55: =+D55*P55 -> 510510 | T55: =+E55*P55 -> 0 | U55: =+F55*P55 -> 510510 | V55: =+G55*P55 -> 510510
B56: SOLDADURA 7018 5/32 | D56: 5 | G56: 5 | O56: =SUM(D56:N56) -> 10 | P56: 105970 | Q56: =O56*P56 -> 1059700 | R56: =C56*P56 -> 0 | S56: =+D56*P56 -> 529850 | T56: =+E56*P56 -> 0 | U56: =+F56*P56 -> 0 | V56: =+G56*P56 -> 529850
B57: THINNER | D57: 1 | O57: =SUM(D57:N57) -> 1 | P57: 37128 | Q57: =O57*P57 -> 37128 | R57: =C57*P57 -> 0 | S57: =+D57*P57 -> 37128 | T57: =+E57*P57 -> 0 | U57: =+F57*P57 -> 0 | V57: =+G57*P57 -> 0
B58: TERMINAL OJO PONHABLE 1/0 | D58: 12 | G58: 25 | O58: =SUM(D58:N58) -> 37 | P58: 8168 | Q58: =O58*P58 -> 302216 | R58: =C58*P58 -> 0 | S58: =+D58*P58 -> 98016 | T58: =+E58*P58 -> 0 | U58: =+F58*P58 -> 0 | V58: =+G58*P58 -> 204200
B59: BOMBA EXTRACTOR DE LIQUIDO | D59: 1 | O59: =SUM(D59:N59) -> 1 | P59: 225862 | Q59: =O59*P59 -> 225862 | R59: =C59*P59 -> 0 | S59: =+D59*P59 -> 225862 | T59: =+E59*P59 -> 0 | U59: =+F59*P59 -> 0 | V59: =+G59*P59 -> 0
B60: BISAGRAS LARGAS 3/4 | D60: 8 | O60: =SUM(D60:N60) -> 8 | P60: 11293 | Q60: =O60*P60 -> 90344 | R60: =C60*P60 -> 0 | S60: =+D60*P60 -> 90344 | T60: =+E60*P60 -> 0 | U60: =+F60*P60 -> 0 | V60: =+G60*P60 -> 0
B61: VIDRIOS DE CARETA NRO 11 | D61: 2 | O61: =SUM(D61:N61) -> 2 | P61: 2321 | Q61: =O61*P61 -> 4642 | R61: =C61*P61 -> 0 | S61: =+D61*P61 -> 4642 | T61: =+E61*P61 -> 0 | U61: =+F61*P61 -> 0 | V61: =+G61*P61 -> 0
B62: VIDRIOS DE CARETA NRO 12 | D62: 2 | O62: =SUM(D62:N62) -> 2 | P62: 2321 | Q62: =O62*P62 -> 4642 | R62: =C62*P62 -> 0 | S62: =+D62*P62 -> 4642 | T62: =+E62*P62 -> 0 | U62: =+F62*P62 -> 0 | V62: =+G62*P62 -> 0
B63: PULSADOR DE TIMBRE | D63: 1 | O63: =SUM(D63:N63) -> 1 | P63: 6188 | Q63: =O63*P63 -> 6188 | R63: =C63*P63 -> 0 | S63: =+D63*P63 -> 6188 | T63: =+E63*P63 -> 0 | U63: =+F63*P63 -> 0 | V63: =+G63*P63 -> 0
B64: AMARRE 40CM | D64: 1 | O64: =SUM(D64:N64) -> 1 | P64: 19802 | Q64: =O64*P64 -> 19802 | R64: =C64*P64 -> 0 | S64: =+D64*P64 -> 19802 | T64: =+E64*P64 -> 0 | U64: =+F64*P64 -> 0 | V64: =+G64*P64 -> 0
B65: CABLE 2 X 18 | D65: 40 | G65: 133.3 | H65: 133.3 | I65: 133.3 | O65: =SUM(D65:N65) -> 439.9 | P65: 2933 | Q65: =O65*P65 -> 1290226.7 | R65: =C65*P65 -> 0 | S65: =+D65*P65 -> 117320 | T65: =+E65*P65 -> 0 | U65: =+F65*P65 -> 0 | V65: =+G65*P65 -> 390968.9
B66: TIMBRE INDUSTRIAL | D66: 1 | O66: =SUM(D66:N66) -> 1 | P66: 37437 | Q66: =O66*P66 -> 37437 | R66: =C66*P66 -> 0 | S66: =+D66*P66 -> 37437 | T66: =+E66*P66 -> 0 | U66: =+F66*P66 -> 0 | V66: =+G66*P66 -> 0
B67: COPA PARA ESPARRAGOS | D67: 4 | O67: =SUM(D67:N67) -> 4 | P67: 3094 | Q67: =O67*P67 -> 12376 | R67: =C67*P67 -> 0 | S67: =+D67*P67 -> 12376 | T67: =+E67*P67 -> 0 | U67: =+F67*P67 -> 0 | V67: =+G67*P67 -> 0
B68: TORNILLOS 5/8 | D68: 4 | O68: =SUM(D68:N68) -> 4 | P68: 6652 | Q68: =O68*P68 -> 26608 | R68: =C68*P68 -> 0 | S68: =+D68*P68 -> 26608 | T68: =+E68*P68 -> 0 | U68: =+F68*P68 -> 0 | V68: =+G68*P68 -> 0
B69: ACEITE QUEMADO | D69: 1 | E69: 4 | F69: 4 | O69: =SUM(D69:N69) -> 9 | P69: 70000 | Q69: =O69*P69 -> 630000 | R69: =C69*P69 -> 0 | S69: =+D69*P69 -> 70000 | T69: =+E69*P69 -> 280000 | U69: =+F69*P69 -> 280000 | V69: =+G69*P69 -> 0
B70: ESPADA 10' OREGON | D70: 1 | O70: =SUM(D70:N70) -> 1 | P70: 464100 | Q70: =O70*P70 -> 464100 | R70: =C70*P70 -> 0 | S70: =+D70*P70 -> 464100 | T70: =+E70*P70 -> 0 | U70: =+F70*P70 -> 0 | V70: =+G70*P70 -> 0
B71: MANIJA MOTOSIERRA OREGON | D71: 1 | O71: =SUM(D71:N71) -> 1 | P71: 232050 | Q71: =O71*P71 -> 232050 | R71: =C71*P71 -> 0 | S71: =+D71*P71 -> 232050 | T71: =+E71*P71 -> 0 | U71: =+F71*P71 -> 0 | V71: =+G71*P71 -> 0
B72: ESPARRAGOS 5/8 | D72: 4 | O72: =SUM(D72:N72) -> 4 | P72: 25990 | Q72: =O72*P72 -> 103960 | R72: =C72*P72 -> 0 | S72: =+D72*P72 -> 103960 | T72: =+E72*P72 -> 0 | U72: =+F72*P72 -> 0 | V72: =+G72*P72 -> 0
B73: FILTRO P/ACEITE ROJO BF 56 3 | D73: 1 | O73: =SUM(D73:N73) -> 1 | P73: 123760 | Q73: =O73*P73 -> 123760 | R73: =C73*P73 -> 0 | S73: =+D73*P73 -> 123760 | T73: =+E73*P73 -> 0 | U73: =+F73*P73 -> 0 | V73: =+G73*P73 -> 0
B74: FILTRO P/COMBUSTIBLE BLANCO A-1212 SP | D74: 2 | O74: =SUM(D74:N74) -> 2 | P74: 69615 | Q74: =O74*P74 -> 139230 | R74: =C74*P74 -> 0 | S74: =+D74*P74 -> 139230 | T74: =+E74*P74 -> 0 | U74: =+F74*P74 -> 0 | V74: =+G74*P74 -> 0
B75: VALVULINA 90 API X 5GL | C75: 1 | O75: =SUM(C75:N75) -> 1 | P75: 585000 | Q75: =O75*P75 -> 585000 | R75: =C75*P75 -> 585000 | S75: =+D75*P75 -> 0 | T75: =+E75*P75 -> 0 | U75: =+F75*P75 -> 0 | V75: =+G75*P75 -> 0
B76: ACEITE QUEMADO | C76: 2 | E76: 2 | O76: =SUM(C76:N76) -> 4 | P76: 65000 | Q76: =O76*P76 -> 260000 | R76: =C76*P76 -> 130000 | S76: =+D76*P76 -> 0 | T76: =+E76*P76 -> 130000 | U76: =+F76*P76 -> 0 | V76: =+G76*P76 -> 0
B77: RESORTE MARTILLO 37 | C77: 6 | O77: =SUM(C77:N77) -> 6 | P77: 13000 | Q77: =O77*P77 -> 78000 | R77: =C77*P77 -> 78000 | S77: =+D77*P77 -> 0 | T77: =+E77*P77 -> 0 | U77: =+F77*P77 -> 0 | V77: =+G77*P77 -> 0
B78: ESFERA MARTILLO 37 | C78: 6 | O78: =SUM(C78:N78) -> 6 | P78: 13000 | Q78: =O78*P78 -> 78000 | R78: =C78*P78 -> 78000 | S78: =+D78*P78 -> 0 | T78: =+E78*P78 -> 0 | U78: =+F78*P78 -> 0 | V78: =+G78*P78 -> 0
B79: BOMBILLOS 20W | C79: 2 | O79: =SUM(C79:N79) -> 2 | P79: 5980 | Q79: =O79*P79 -> 11960 | R79: =C79*P79 -> 11960 | S79: =+D79*P79 -> 0 | T79: =+E79*P79 -> 0 | U79: =+F79*P79 -> 0 | V79: =+G79*P79 -> 0
B80: CADENA SIERRA NEUMATICA | C80: 1 | F80: 2 | O80: =SUM(C80:N80) -> 3 | P80: 101400 | Q80: =O80*P80 -> 304200 | R80: =C80*P80 -> 101400 | S80: =+D80*P80 -> 0 | T80: =+E80*P80 -> 0 | U80: =+F80*P80 -> 202800 | V80: =+G80*P80 -> 0
B81: AGUJA DE CAÑAMO MD | C81: 2 | O81: =SUM(C81:N81) -> 2 | P81: 3250 | Q81: =O81*P81 -> 6500 | R81: =C81*P81 -> 6500 | S81: =+D81*P81 -> 0 | T81: =+E81*P81 -> 0 | U81: =+F81*P81 -> 0 | V81: =+G81*P81 -> 0
B82: AGUJA DE CAÑAMO GDE | C82: 1 | O82: =SUM(C82:N82) -> 1 | P82: 6500 | Q82: =O82*P82 -> 6500 | R82: =C82*P82 -> 6500 | S82: =+D82*P82 -> 0 | T82: =+E82*P82 -> 0 | U82: =+F82*P82 -> 0 | V82: =+G82*P82 -> 0
B83: CAÑAMO | C83: 2 | F83: 2 | O83: =SUM(C83:N83) -> 4 | P83: 10400 | Q83: =O83*P83 -> 41600 | R83: =C83*P83 -> 20800 | S83: =+D83*P83 -> 0 | T83: =+E83*P83 -> 0 | U83: =+F83*P83 -> 20800 | V83: =+G83*P83 -> 0
B84: ACCIONADOR P/CORNETA | C84: 1 | O84: =SUM(C84:N84) -> 1 | P84: 32500 | Q84: =O84*P84 -> 32500 | R84: =C84*P84 -> 32500 | S84: =+D84*P84 -> 0 | T84: =+E84*P84 -> 0 | U84: =+F84*P84 -> 0 | V84: =+G84*P84 -> 0
B85: GRILLETE 7/8 | C85: 2 | E85: 2 | F85: 1 | G85: 1 | O85: =SUM(C85:N85) -> 6 | P85: 37050 | Q85: =O85*P85 -> 222300 | R85: =C85*P85 -> 74100 | S85: =+D85*P85 -> 0 | T85: =+E85*P85 -> 74100 | U85: =+F85*P85 -> 37050 | V85: =+G85*P85 -> 37050
B86: TORNILLOS ECLIPSAS/ARANDELAS/TUERCAS | C86: 48 | O86: =SUM(C86:N86) -> 48 | P86: 2210 | Q86: =O86*P86 -> 106080 | R86: =C86*P86 -> 106080 | S86: =+D86*P86 -> 0 | T86: =+E86*P86 -> 0 | U86: =+F86*P86 -> 0 | V86: =+G86*P86 -> 0
B87: FRESA TUSTENO RECTO | C87: 1 | O87: =SUM(C87:N87) -> 1 | P87: 56550 | Q87: =O87*P87 -> 56550 | R87: =C87*P87 -> 56550 | S87: =+D87*P87 -> 0 | T87: =+E87*P87 -> 0 | U87: =+F87*P87 -> 0 | V87: =+G87*P87 -> 0
B88: FRESA TUSTENO CONICA | C88: 1 | O88: =SUM(C88:N88) -> 1 | P88: 63700 | Q88: =O88*P88 -> 63700 | R88: =C88*P88 -> 63700 | S88: =+D88*P88 -> 0 | T88: =+E88*P88 -> 0 | U88: =+F88*P88 -> 0 | V88: =+G88*P88 -> 0
B89: llave expansiva de 10" | C89: 1 | O89: =SUM(C89:N89) -> 1 | P89: 35100 | Q89: =O89*P89 -> 35100 | R89: =C89*P89 -> 35100 | S89: =+D89*P89 -> 0 | T89: =+E89*P89 -> 0 | U89: =+F89*P89 -> 0 | V89: =+G89*P89 -> 0
B90: hombre solo | C90: 1 | F90: 1 | O90: =SUM(C90:N90) -> 2 | P90: 52000 | Q90: =O90*P90 -> 104000 | R90: =C90*P90 -> 52000 | S90: =+D90*P90 -> 0 | T90: =+E90*P90 -> 0 | U90: =+F90*P90 -> 52000 | V90: =+G90*P90 -> 0
B91: aceite hidraulico marca mobil | C91: 1 | O91: =SUM(C91:N91) -> 1 | P91: 507000 | Q91: =O91*P91 -> 507000 | R91: =C91*P91 -> 507000 | S91: =+D91*P91 -> 0 | T91: =+E91*P91 -> 0 | U91: =+F91*P91 -> 0 | V91: =+G91*P91 -> 0
B92: llave de cadena 22" | C92: 1 | O92: =SUM(C92:N92) -> 1 | P92: 51600 | Q92: =O92*P92 -> 51600 | R92: =C92*P92 -> 51600 | S92: =+D92*P92 -> 0 | T92: =+E92*P92 -> 0 | U92: =+F92*P92 -> 0 | V92: =+G92*P92 -> 0
B93: recarga de extintores 10 libras cada uno | C93: 3 | O93: =SUM(C93:N93) -> 3 | P93: 65000 | Q93: =O93*P93 -> 195000 | R93: =C93*P93 -> 195000 | S93: =+D93*P93 -> 0 | T93: =+E93*P93 -> 0 | U93: =+F93*P93 -> 0 | V93: =+G93*P93 -> 0
B94: cintas rojas aislantes | C94: 2 | G94: 3 | O94: =SUM(C94:N94) -> 5 | P94: 5850 | Q94: =O94*P94 -> 29250 | R94: =C94*P94 -> 11700 | S94: =+D94*P94 -> 0 | T94: =+E94*P94 -> 0 | U94: =+F94*P94 -> 0 | V94: =+G94*P94 -> 17550
B95: cintas amarillas aislantes | C95: 2 | G95: 3 | O95: =SUM(C95:N95) -> 5 | P95: 5850 | Q95: =O95*P95 -> 29250 | R95: =C95*P95 -> 11700 | S95: =+D95*P95 -> 0 | T95: =+E95*P95 -> 0 | U95: =+F95*P95 -> 0 | V95: =+G95*P95 -> 17550
B96: terminal de ojo ponchable 2 awg | C96: 12 | G96: 25 | O96: =SUM(C96:N96) -> 37 | P96: 5850 | Q96: =O96*P96 -> 216450 | R96: =C96*P96 -> 70200 | S96: =+D96*P96 -> 0 | T96: =+E96*P96 -> 0 | U96: =+F96*P96 -> 0 | V96: =+G96*P96 -> 146250
B97: llave bristol 6mm | C97: 1 | O97: =SUM(C97:N97) -> 1 | P97: 11050 | Q97: =O97*P97 -> 11050 | R97: =C97*P97 -> 11050 | S97: =+D97*P97 -> 0 | T97: =+E97*P97 -> 0 | U97: =+F97*P97 -> 0 | V97: =+G97*P97 -> 0
B98: hoja de bistury | C98: 1 | O98: =SUM(C98:N98) -> 1 | P98: 3250 | Q98: =O98*P98 -> 3250 | R98: =C98*P98 -> 3250 | S98: =+D98*P98 -> 0 | T98: =+E98*P98 -> 0 | U98: =+F98*P98 -> 0 | V98: =+G98*P98 -> 0
B99: empaque perforadora | C99: 2 | O99: =SUM(C99:N99) -> 2 | P99: 19500 | Q99: =O99*P99 -> 39000 | R99: =C99*P99 -> 39000 | S99: =+D99*P99 -> 0 | T99: =+E99*P99 -> 0 | U99: =+F99*P99 -> 0 | V99: =+G99*P99 -> 0
B100: cable de timbre | C100: 100 | O100: =SUM(C100:N100) -> 100 | P100: 1702 | Q100: =O100*P100 -> 170200 | R100: =C100*P100 -> 170200 | S100: =+D100*P100 -> 0 | T100: =+E100*P100 -> 0 | U100: =+F100*P100 -> 0 | V100: =+G100*P100 -> 0
...

Sheet ENERGIA 2026
A1: CALCULO CONSUMO ELECTRICO VS PRODUCCIÓN 2026
A3: MES | B3: CONSUMO DIARIO Kw | C3: CONSUMO MENSUAL Kw | D3: COSTO KW 2025 | E3: VALOR A PAGAR | F3: VALOR A PAGAR EN MM | G3: PRODUCION MES TON | H3: PRODUCION ANUAL MES TON | I3: COSTO TONELADA VS ENERGIA
A4: ENERO | B4: =+C4/31 -> 911.6129 | C4: 28260 | D4: =+E4/C4 -> 1047.5311 | E4: 29603230 | F4: =+E4/10000 -> 2960.323 | G4: =+'PRODUC ACUMULADA'!B5 -> 1698.66 | H4: =+G16 -> 10119.57 | I4: =+E4/G4 -> 17427.402
A5: FEBRERO | B5: =+C5/29 -> 1025.8621 | C5: 29750 | D5: =+E5/C5 -> 987.16908 | E5: 29368280 | F5: =+E5/10000 -> 2936.828 | G5: =+'PRODUC ACUMULADA'!B6 -> 1830.15 | I5: =+E5/G5 -> 16046.925
A6: MARZO | B6: =+C6/31 -> 1198.129 | C6: 37142 | D6: =+E6/C6 -> 1031.6044 | E6: 38315850 | F6: =+E6/10000 -> 3831.585 | G6: =+'PRODUC ACUMULADA'!B7 -> 1898.77 | I6: =+E6/G6 -> 20179.3
A7: ABRIL | B7: =+C7/30 -> 1117.2333 | C7: 33517 | D7: =+E7/C7 -> 1100.7474 | E7: 36893750 | F7: =+E7/10000 -> 3689.375 | G7: =+'PRODUC ACUMULADA'!B8 -> 1800.91 | I7: =+E7/G7 -> 20486.171
A8: MAYO | B8: =+C8/31 -> 1005 | C8: 31155 | D8: =+E8/C8 -> 1011.16 | E8: 31502690 | F8: =+E8/10000 -> 3150.269 | G8: =+'PRODUC ACUMULADA'!B9 -> 1964.11 | I8: =+E8/G8 -> 16039.168
A9: JUNIO | B9: =+C9/30 -> 0 | D9: =+E9/C9 -> #DIV/0! | F9: =+E9/10000 -> 0 | G9: =+'PRODUC ACUMULADA'!B10 -> 926.97 | I9: =+E9/G9 -> 0
A10: JULIO | B10: =+C10/31 -> 0 | D10: =+E10/C10 -> #DIV/0! | F10: =+E10/10000 -> 0 | G10: =+'PRODUC ACUMULADA'!B11 -> 0 | I10: =+E10/G10 -> #DIV/0!
A11: AGOSTO | B11: =+C11/31 -> 0 | D11: =+E11/C11 -> #DIV/0! | F11: =+E11/10000 -> 0 | G11: =+'PRODUC ACUMULADA'!B12 -> 0 | I11: =+E11/G11 -> #DIV/0!
A12: SEPTIEMBRE | B12: =+C12/30 -> 0 | D12: =+E12/C12 -> #DIV/0! | F12: =+E12/10000 -> 0 | G12: =+'PRODUC ACUMULADA'!B13 -> 0 | I12: =+E12/G12 -> #DIV/0!
A13: OCTUBRE | B13: =+C13/31 -> 0 | D13: =+E13/C13 -> #DIV/0! | F13: =+E13/10000 -> 0 | G13: =+'PRODUC ACUMULADA'!B14 -> 0 | I13: =+E13/G13 -> #DIV/0!
A14: NOVIEMBRE | B14: =+C14/30 -> 0 | D14: =+E14/C14 -> #DIV/0! | F14: =+E14/10000 -> 0 | G14: =+'PRODUC ACUMULADA'!B15 -> 0 | I14: =+E14/G14 -> #DIV/0!
A15: DICIEMBRE | B15: =+C15/30 -> 0 | D15: =+E15/C15 -> #DIV/0! | F15: =+E15/10000 -> 0 | G15: =+'PRODUC ACUMULADA'!B16 -> 0 | I15: =+E15/G15 -> #DIV/0!
A16: TOTAL | C16: =SUM(C4:C15) -> 159824 | E16: =SUM(E4:E15) -> 165683800 | G16: =SUM(G4:G15) -> 10119.57 | H16: =+C16/H4 -> 15.793556

Sheet MADERA
B1: VALOR COMERCIAL
B3: MES | C3: MINA | D3: Unid | F3: PART. PORCENTUAL | G3: VALOR | H3: TOTAL MES | J3: ITEMS | L3: V/R COMERCIAL | M3: V/R SR ALDEMAR
B4: Enero | C4: Palancas | D4: 841 | E4: =+D4+D5+D6 -> 2176 | F4: =D4/$E$4 -> 0.38648897 | G4: =+D4*L4 -> 21866000 | H4: =+G4+G5+G6 -> 35216000 | J4: PRECIO PALANCA | L4: 26000 | M4: 4000
C5: Tabla | D5: 1335 | F5: =D5/$E$4 -> 0.61351103 | G5: =+D5*L5 -> 13350000 | J5: PRECIO DE TABLA | L5: 10000 | M5: 3000
C6: Riel | D6: 0 | F6: =D6/$E$4 -> 0 | G6: =+D6*L6 -> 0 | J6: PRECIO DE RIEL | L6: 7000 | M6: 3000
B7: Febrero | C7: Palancas | D7: 1124 | E7: =+D7+D8+D9 -> 2352 | F7: =D7/$E$7 -> 0.47789116 | G7: =+D7*L4 -> 29224000 | H7: =+G7+G8+G9 -> 41532000 | J7: precio varas | L7: 2000 | M7: 2000
C8: Tabla | D8: 1226 | F8: =D8/$E$7 -> 0.5212585 | G8: =+D8*L5 -> 12260000 | J8: precio Tabla especial | L8: 2000 | M8: 4000
C9: VARAS DE 4 MTRS | D9: 2 | F9: =D9/$E$7 -> 0.00085034014 | G9: =+(D9*24000) -> 48000 | J9: precio Tacos | L9: 2000 | M9: 4000
B10: Marzo | C10: Palancas | D10: 1101 | E10: =+D10+D11+D12 -> 2674 | F10: =D10/$E$10 -> 0.41174271 | G10: =+D10*L4 -> 28626000 | H10: =+G10+G11+G12 -> 44356000
C11: Tablas | D11: 1573 | F11: =D11/$E$10 -> 0.58825729 | G11: =+D11*L5 -> 15730000
C12: Riel | D12: 0 | F12: =D12/$E$10 -> 0 | G12: =+D12*L6 -> 0 | J12: MES | K12: TOTAL | L12: PRODUCCION | M12: V/R * TONELADA
B13: Abril | C13: Palancas | D13: 1045 | E13: =+D13+D14+D15 -> 2568 | F13: =D13/$E$13 -> 0.40693146 | G13: =+D13*L4 -> 27170000 | H13: =+G13+G14+G15 -> 42400000 | J13: ENERO | K13: =+H4 -> 35216000 | L13: =+'PRODUC ACUMULADA'!B5 -> 1698.66 | M13: =+K13/L13 -> 20731.636
C14: Tablas | D14: 1523 | F14: =D14/$E$13 -> 0.59306854 | G14: =+D14*L5 -> 15230000 | J14: FEBRERO | K14: =+H7 -> 41532000 | L14: =+'PRODUC ACUMULADA'!B6 -> 1830.15 | M14: =+K14/L14 -> 22693.222
C15: Riel | D15: 0 | F15: =D15/$E$13 -> 0 | G15: =+D15*L6 -> 0 | J15: MARZO | K15: =+H10 -> 44356000 | L15: =+'PRODUC ACUMULADA'!B7 -> 1898.77 | M15: =+K15/L15 -> 23360.386
B16: Mayo | C16: Palancas | D16: 871 | E16: =+D16+D17+D18 -> 2166 | F16: =D16/$E$16 -> 0.40212373 | G16: =+D16*L4 -> 22646000 | H16: =+G16+G17+G18 -> 34996000 | J16: ABRIL | K16: =+H13 -> 42400000 | L16: =+'PRODUC ACUMULADA'!B8 -> 1800.91 | M16: =+K16/L16 -> 23543.653
C17: Tablas | D17: 1220 | F17: =D17/$E$16 -> 0.56325023 | G17: =+D17*L5 -> 12200000 | J17: MAYO | K17: =+H16 -> 34996000 | L17: =+'PRODUC ACUMULADA'!B9 -> 1964.11 | M17: =+K17/L17 -> 17817.739
C18: Tacos | D18: 75 | F18: =D18/$E$16 -> 0.034626039 | G18: =+D18*L9 -> 150000 | J18: JUNIO | K18: =+H19 -> 0 | L18: =+'PRODUC ACUMULADA'!B10 -> 926.97 | M18: =+K18/L18 -> 0
B19: Junio | C19: Palancas | D19: 0 | E19: =+D19+D20+D21 -> 0 | F19: =+D19/E19 -> #DIV/0! | G19: =+D19*L4 -> 0 | H19: =+G19+G20+G21 -> 0 | J19: JULIO | K19: =+H22 -> 0 | L19: =+'PRODUC ACUMULADA'!B11 -> 0 | M19: =+K19/L19 -> #DIV/0!
C20: Tablas | D20: 0 | F20: =+D20/E19 -> #DIV/0! | G20: =+D20*L5 -> 0 | J20: AGOSTO | K20: =+H25 -> 0 | L20: =+'PRODUC ACUMULADA'!B12 -> 0 | M20: =+K20/L20 -> #DIV/0!
C21: Riel | D21: 0 | F21: =+D21/E19 -> #DIV/0! | G21: =+(D21*L6) -> 0 | J21: SEPTIEMBRE | K21: =+H28 -> 0 | L21: =+'PRODUC ACUMULADA'!B13 -> 0 | M21: =+K21/L21 -> #DIV/0!
B22: Julio | C22: Palancas | D22: 0 | E22: =+D22+D23+D24 -> 0 | F22: =+D22/E22 -> #DIV/0! | G22: =+D22*L4 -> 0 | H22: =+G22+G23+G24 -> 0 | J22: OCTUBRE | K22: =+H31 -> 0 | L22: =+'PRODUC ACUMULADA'!B14 -> 0 | M22: =+K22/L22 -> #DIV/0!
C23: Tablas | D23: 0 | F23: =+D23/E22 -> #DIV/0! | G23: =+D23*L5 -> 0 | J23: NOVIEMBRE | K23: =+H34 -> 0 | L23: =+'PRODUC ACUMULADA'!B15 -> 0 | M23: =+K23/L23 -> #DIV/0!
C24: Riel | D24: 0 | F24: =+D24/E22 -> #DIV/0! | G24: =+D24*L6 -> 0 | J24: DICIEMBRE | K24: =+H37 -> 0 | L24: =+'PRODUC ACUMULADA'!B16 -> 0 | M24: =+K24/L24 -> #DIV/0!
B25: Agosto | C25: Palancas | D25: 0 | E25: =+D25+D26+D27 -> 0 | F25: =+D25/E25 -> #DIV/0! | G25: =+D25*L4 -> 0 | H25: =+G25+G26+G27 -> 0 | J25: TOTAL | K25: =SUM(K13:K24) -> 198500000 | L25: =SUM(L13:L24) -> 10119.57 | M25: =SUM(M13:M24) -> #DIV/0!
C26: Tablas | D26: 0 | F26: =+D26/E25 -> #DIV/0! | G26: =+D26*L5 -> 0
C27: Riel | D27: 0 | F27: =+D27/E25 -> #DIV/0! | G27: =+D27*L6 -> 0
B28: Septiembre | C28: Palancas | D28: 0 | E28: =+D28+D29+D30 -> 0 | F28: =+D28/E28 -> #DIV/0! | G28: =+D28*L4 -> 0 | H28: =+G28+G29+G30 -> 0
C29: Tablas | D29: 0 | F29: =+D29/E28 -> #DIV/0! | G29: =+D29*L5 -> 0
C30: Riel | D30: 0 | F30: =+D30/E28 -> #DIV/0! | G30: =+D30*L6 -> 0
B31: Octubre | C31: Palancas | D31: 0 | E31: =+D31+D32+D33 -> 0 | F31: =+D31/E31 -> #DIV/0! | G31: =+D31*L4 -> 0 | H31: =+G31+G32+G33 -> 0
C32: Tablas | D32: 0 | F32: =+D32/E31 -> #DIV/0! | G32: =+D32*L5 -> 0
C33: Riel | D33: 0 | F33: =+D33/E31 -> #DIV/0! | G33: =+D33*L6 -> 0
B34: Noviembre | C34: Palancas | D34: 0 | E34: =+D34+D35+D36 -> 0 | F34: =+D34/E34 -> #DIV/0! | G34: =+D34*L4 -> 0 | H34: =+G34+G35+G36 -> 0
C35: Tablas | D35: 0 | F35: =+D35/E34 -> #DIV/0! | G35: =+D35*L5 -> 0
C36: Riel | D36: 0 | F36: =+D36/E34 -> #DIV/0! | G36: =+D36*L6 -> 0
B37: Diciembre | C37: Palancas | D37: 0 | E37: =+D37+D38+D39 -> 0 | F37: =+D37/E37 -> #DIV/0! | G37: =+D37*L4 -> 0 | H37: =+G37+G38+G39 -> 0
C38: Tablas | D38: 0 | F38: =+D38/E37 -> #DIV/0! | G38: =+D38*L5 -> 0
C39: Riel | D39: 0 | F39: =+D39/E37 -> #DIV/0! | G39: =+D39*L6 -> 0
C40: TOTAL 2025 | D40: =SUM(D4:D39) -> 11936 | F40: =SUM(F4:F39) -> #DIV/0! | G40: =SUM(G4:G39) -> 198500000 | H40: =SUM(H4:H39) -> 198500000
K71: 0

Sheet COMBUSTIBLE
C2: MES | D2: TOTAL | E2: PRODUCCION | F2: V/R * TONELADA
B3: 1 | C3: ENERO | D3: 3431124 | E3: =+'PRODUC ACUMULADA'!B5 -> 1698.66 | F3: =+D3/E3 -> 2019.9004
B4: 2 | C4: FEBRERO | D4: 12535782 | E4: =+'PRODUC ACUMULADA'!B6 -> 1830.15 | F4: =+D4/E4 -> 6849.5927
B5: 3 | C5: MARZO | D5: 4480816 | E5: =+'PRODUC ACUMULADA'!B7 -> 1898.77 | F5: =+D5/E5 -> 2359.8519
B6: 4 | C6: ABRIL | D6: 4609346 | E6: =+'PRODUC ACUMULADA'!B8 -> 1800.91 | F6: =+D6/E6 -> 2559.4538
B7: 5 | C7: MAYO | D7: 11596960 | E7: =+'PRODUC ACUMULADA'!B9 -> 1964.11 | F7: =+D7/E7 -> 5904.4351
B8: 6 | C8: JUNIO | D8: 0 | E8: =+'PRODUC ACUMULADA'!B10 -> 926.97 | F8: =+D8/E8 -> 0
B9: 7 | C9: JULIO | D9: 0 | E9: =+'PRODUC ACUMULADA'!B11 -> 0 | F9: =+D9/E9 -> #DIV/0!
B10: 8 | C10: AGOSTO | D10: 0 | E10: =+'PRODUC ACUMULADA'!B12 -> 0 | F10: =+D10/E10 -> #DIV/0!
B11: 9 | C11: SEPTIEMBRE | D11: 0 | E11: =+'PRODUC ACUMULADA'!B13 -> 0 | F11: =+D11/E11 -> #DIV/0!
B12: 10 | C12: OCTUBRE | D12: 0 | E12: =+'PRODUC ACUMULADA'!B14 -> 0 | F12: =+D12/E12 -> #DIV/0!
B13: 11 | C13: NOVIEMBRE | D13: 0 | E13: =+'PRODUC ACUMULADA'!B15 -> 0 | F13: =+D13/E13 -> #DIV/0!
B14: 12 | C14: DICIEMBRE | D14: 0 | E14: =+'PRODUC ACUMULADA'!B16 -> 0 | F14: =+D14/E14 -> #DIV/0!
C15: TOTAL | D15: =SUM(D3:D14) -> 36654028 | E15: =SUM(E3:E14) -> 10119.57 | F15: =SUM(F3:F14) -> #DIV/0!

Sheet PAJARITA
B1: INSUMOS | C1: ENERO | D1: FEBRERO | E1: MARZO | F1: ABRIL | G1: MAYO | H1: JUNIO | I1: JULIO | J1: AGOSTO | K1: SEPTIEMBRE | L1: OCTUBRE | M1: NOVIEMBRE | N1: DICIEMBRE | O1: TOTAL | P1: PRECIO UNITARIO | Q1: TOTAL | R1: ENERO EN PESOS | S1: FEBRERO EN PESOS | T1: MARZO EN PESOS | U1: ABRIL EN PESOS | V1: MAYO EN PESOS | W1: JUNIO EN PESOS | X1: JULIO EN PESOS | Y1: AGOSTO EN PESOS | Z1: SEPTIEMBRE EN PESOS | AA1: OCTUBRE EN PESOS | AB1: NOVIEMBRE EN PESOS | AC1: DICIEMBRE EN PESOS
B2: ITEM | C2: ENERO | D2: FEBRERO | E2: MARZO | F2: ABRIL | G2: MAYO | H2: JUNIO | I2: JULIO | J2: AGOSTO | K2: SEPTIEMBRE | L2: OCTUBRE | M2: NOVIEMBRE | N2: DICIEMBRE | O2: TOTAL | P2: PRECIO UNITARIO | Q2: TOTAL | R2: ENERO EN PESOS | S2: FEBRERO EN PESOS | T2: MARZO EN PESOS | U2: ABRIL EN PESOS | V2: MAYO EN PESOS | W2: JUNIO EN PESOS | X2: JULIO EN PESOS | Y2: AGOSTO EN PESOS | Z2: SEPTIEMBRE EN PESOS | AA2: OCTUBRE EN PESOS | AB2: NOVIEMBRE EN PESOS | AC2: DICIEMBRE EN PESOS
B3: ACEITE MOVIL P/FRENOS PAJARITA | D3: 1 | O3: =+C3+D3+E3+F3+G3+H3+I3+J3+K3+L3+M3+N3 -> 1 | P3: 247520 | Q3: =O3*P3 -> 247520 | R3: =C3*P3 -> 0 | S3: =+D3*P3 -> 247520
B4: FILTRO BF 7951 | D4: 1 | O4: =+C4+D4+E4+F4+G4+H4+I4+J4+K4+L4+M4+N4 -> 1 | P4: 133600 | Q4: =O4*P4 -> 133600 | R4: =C4*P4 -> 0 | S4: =+D4*P4 -> 133600
B5: FILTRO BF 7965 | D5: 1 | O5: =+C5+D5+E5+F5+G5+H5+I5+J5+K5+L5+M5+N5 -> 1 | P5: 134000 | Q5: =O5*P5 -> 134000 | R5: =C5*P5 -> 0 | S5: =+D5*P5 -> 134000
B6: FILTRO B 7350 | D6: 1 | O6: =+C6+D6+E6+F6+G6+H6+I6+J6+K6+L6+M6+N6 -> 1 | P6: 101360 | Q6: =O6*P6 -> 101360 | R6: =C6*P6 -> 0 | S6: =+D6*P6 -> 101360
B7: FILTRO F8109 | D7: 1 | O7: =+C7+D7+E7+F7+G7+H7+I7+J7+K7+L7+M7+N7 -> 1 | P7: 189936 | Q7: =O7*P7 -> 189936 | R7: =C7*P7 -> 0 | S7: =+D7*P7 -> 189936
B8: FILTRO DA 9109 | D8: 1 | O8: =+C8+D8+E8+F8+G8+H8+I8+J8+K8+L8+M8+N8 -> 1 | P8: 189936 | Q8: =O8*P8 -> 189936 | R8: =C8*P8 -> 0 | S8: =+D8*P8 -> 189936
B9: REFIGRIGERANTE | D9: 1 | O9: =+C9+D9+E9+F9+G9+H9+I9+J9+K9+L9+M9+N9 -> 1 | P9: 52000 | Q9: =O9*P9 -> 52000 | R9: =C9*P9 -> 0 | S9: =+D9*P9 -> 52000
B10: LLANTAS DELANTERAS MARCA GOODYEAR | D10: 2 | O10: =+C10+D10+E10+F10+G10+H10+I10+J10+K10+L10+M10+N10 -> 2 | P10: 2480000 | Q10: =O10*P10 -> 4960000 | R10: =C10*P10 -> 0 | S10: =+D10*P10 -> 4960000
B11: CUCHILLA | C11: 1 | O11: =+C11+D11+E11+F11+G11+H11+I11+J11+K11+L11+M11+N11 -> 1 | P11: 1200000 | Q11: =O11*P11 -> 1200000 | R11: =C11*P11 -> 1200000 | S11: =+D11*P11 -> 0
R12: =SUM(R3:R11) -> 1200000 | S12: =SUM(S3:S11) -> 6008352 | T12: =SUM(T3:T5) -> 0 | U12: =SUM(U3:U5) -> 0 | V12: =SUM(V3:V5) -> 0 | W12: =SUM(W3:W5) -> 0 | X12: =SUM(X3:X5) -> 0 | Y12: =SUM(Y3:Y5) -> 0 | Z12: =SUM(Z3:Z5) -> 0 | AA12: =SUM(AA3:AA5) -> 0 | ... AC12: =SUM(AC3:AC5) -> 0
J16: MES | K16: TOTAL | L16: PRODUCCION | M16: V/R * TONELADA
I17: 1 | J17: ENERO | K17: =+R12 -> 1200000 | L17: =+'PRODUC ACUMULADA'!B5 -> 1698.66 | M17: =+K17/L17 -> 706.43919
I18: 2 | J18: FEBRERO | K18: =+S12 -> 6008352 | L18: =+'PRODUC ACUMULADA'!B6 -> 1830.15 | M18: =+K18/L18 -> 3282.9834
I19: 3 | J19: MARZO | K19: =+T12 -> 0 | L19: =+'PRODUC ACUMULADA'!B7 -> 1898.77 | M19: =+K19/L19 -> 0
I20: 4 | J20: ABRIL | K20: =+U12 -> 0 | L20: =+'PRODUC ACUMULADA'!B8 -> 1800.91 | M20: =+K20/L20 -> 0
I21: 5 | J21: MAYO | K21: =+V12 -> 0 | L21: =+'PRODUC ACUMULADA'!B9 -> 1964.11 | M21: =+K21/L21 -> 0
I22: 6 | J22: JUNIO | K22: =+W12 -> 0 | L22: =+'PRODUC ACUMULADA'!B10 -> 926.97 | M22: =+K22/L22 -> 0
I23: 7 | J23: JULIO | K23: =+X12 -> 0 | L23: =+'PRODUC ACUMULADA'!B11 -> 0 | M23: =+K23/L23 -> #DIV/0!
I24: 8 | J24: AGOSTO | K24: =+Y12 -> 0 | L24: =+'PRODUC ACUMULADA'!B12 -> 0 | M24: =+K24/L24 -> #DIV/0!
I25: 9 | J25: SEPTIEMBRE | K25: =+Z12 -> 0 | L25: =+'PRODUC ACUMULADA'!B13 -> 0 | M25: =+K25/L25 -> #DIV/0!
I26: 10 | J26: OCTUBRE | K26: =+AA12 -> 0 | L26: =+'PRODUC ACUMULADA'!B14 -> 0 | M26: =+K26/L26 -> #DIV/0!
I27: 11 | J27: NOVIEMBRE | K27: =+AB12 -> 0 | L27: =+'PRODUC ACUMULADA'!B15 -> 0 | M27: =+K27/L27 -> #DIV/0!
I28: 12 | J28: DICIEMBRE | K28: =+AC12 -> 0 | L28: =+'PRODUC ACUMULADA'!B16 -> 0 | M28: =+K28/L28 -> #DIV/0!
J29: TOTAL | K29: =SUM(K17:K28) -> 7208352 | L29: =SUM(L17:L28) -> 10119.57 | M29: =SUM(M17:M28) -> #DIV/0!

Sheet CALCULO MADERA
F3: OPERADOR PAJARITA | I3: VALOR CORTE MADERA FEBRERO
B4: ITEMS | C4: DESCRICION | D4: V/R TOTAL MES | F4: SALARIO OPERADOR | G4: 1927055 | I4: PALACA ESP | J4: =+MADERA!D7*MADERA!M4 -> 4496000
B5: 1 | C5: SALARIO OPERADOR PAJARITA + RESTAURANTE | D5: =+G4+G6 -> 2141555 | F5: CARGA PRESTACIONAL | G5: =+(1750000)*54.29% -> 950075 | I5: TABLA | J5: =+MADERA!D8*MADERA!M5 -> 3678000
B6: =+B5+1 -> 2 | C6: CARGA PRESTACION SOCIALES OPERADOR | D6: =+G5 -> 950075 | F6: RESTAURANTE | G6: =107250*2 -> 214500 | I6: =+MADERA!C9 -> VARAS DE 4 MTRS | J6: =+MADERA!D9*MADERA!M5 -> 6000
B7: =+B6+1 -> 3 | C7: COMBUSTIBLE | D7: =151*12011 -> 1813661 | F7: TOTAL MES | G7: =SUM(G4:G6) -> 3091630 | I7: TOTAL CONSUMO | J7: =SUM(J4:J6) -> 8180000
B8: =+B7+1 -> 4 | C8: LLANTAS | D8: =+(11700000/12) -> 975000 | F8: V/R HORA | G8: =+G7/240 -> 12881.792
B9: =+B8+1 -> 5 | C9: CAMBIO ACEITE | D9: =+(1234000*4)/12 -> 411333.33
B10: =+B9+1 -> 6 | C10: MANTENIMIENTO GRAL | D10: =6699971/12 -> 558330.92
B11: =+B10+1 -> 7 | C11: ALQUILER PAJARITA | D11: 14000000
B12: =+B11+1 -> 8 | C12: SALARIO PATIEROS + RESTAURANTE | D12: =+G15+G17 -> 4917310
B13: =+B12+1 -> 9 | C13: CARGA PRESTACION SOCIALES PATIEROS | D13: =+G16 -> 1900150
B14: =+B13+1 -> 10 | C14: COSTO DEL CORTE MADERA | D14: =+J7 -> 8180000 | F14: PATIEROS
C15: TOTAL COSTO CORTE MADERA MINA | D15: =SUM(D5:D14) -> 35847415 | F15: SALARIO PATIEROS | G15: 3825310
F16: CARGA PRESTACIONAL | G16: =+(3500000)*54.29% -> 1900150
F17: RESTAURANTE | G17: 1092000
F18: TOTAL MES | G18: =SUM(G15:G17) -> 6817460
